Workbook

Sheet Dashboard
A1: TAX & INSURANCE OPTIMIZER - LIFE OS
A2: Florida ACA Silver CSR 94% Qualification Tracker
A4: KEY METRICS
A6: Tax Year: | C6: 2025
A7: Filing Status: | C7: Single
A8: Target Program: | C8: ACA Silver CSR 94%
A9: Target MAGI Range: | C9: $15,650 - $20,121
A11: CURRENT STATUS
A13: Gross Rental Income: | C13: =MAGI!C7 -> 0
A14: Total Expenses: | C14: =MAGI!C11 -> 0
A15: Net Rental Income: | C15: =MAGI!C13 -> 0
A16: Other Income: | C16: =MAGI!C9 -> 0
A17: Current MAGI: | C17: =MAGI!C15 -> 0
A19: STATUS: | C19: =IF(MAGI!C15<15650,"❌ COVERAGE GAP - TOO LOW",IF(MAGI!C15<=20121,"✅ OPTIMAL RANGE",IF(MAGI!C15<=23475,"⚠️ STILL CSR 94%","❌ ABOVE TARGET"))) -> ❌ COVERAGE GAP - TOO LOW
A21: FLORIDA 2026 ACA THRESHOLDS
A23: Program | B23: Min MAGI | C23: Max MAGI | D23: FPL %
A24: Coverage Gap (NO HELP) | B24: $0 | C24: $15,649 | D24: <100%
A25: ACA Silver CSR 94% | B25: $15,650 | C25: $23,475 | D25: 100-150%
A26: ACA Silver CSR 87% | B26: $23,476 | C26: $31,300 | D26: 150-200%
A27: ACA Silver CSR 73% | B27: $31,301 | C27: $39,125 | D27: 200-250%
A28: ACA Subsidy Only | B28: $39,126 | C28: $62,600 | D28: 250-400%
A30: ⚠️ ENROLLMENT DEADLINE: | C30: December 15, 2025
A31: Enroll at: | C31: healthcare.gov

Sheet Income
A1: RENTAL INCOME TRACKING
A3: Property Address: | C3: Enter Address Here
A5: Month | B5: Gross Rent | C5: Vacancy Days | D5: Vacancy Loss | E5: Other Income | F5: Net Collected
A6: January | B6: 0 | C6: 0 | D6: =IF(C6>0,B6/30*C6,0) -> 0 | E6: 0 | F6: =B6-D6+E6 -> 0
A7: February | B7: 0 | C7: 0 | D7: =IF(C7>0,B7/30*C7,0) -> 0 | E7: 0 | F7: =B7-D7+E7 -> 0
A8: March | B8: 0 | C8: 0 | D8: =IF(C8>0,B8/30*C8,0) -> 0 | E8: 0 | F8: =B8-D8+E8 -> 0
A9: April | B9: 0 | C9: 0 | D9: =IF(C9>0,B9/30*C9,0) -> 0 | E9: 0 | F9: =B9-D9+E9 -> 0
A10: May | B10: 0 | C10: 0 | D10: =IF(C10>0,B10/30*C10,0) -> 0 | E10: 0 | F10: =B10-D10+E10 -> 0
A11: June | B11: 0 | C11: 0 | D11: =IF(C11>0,B11/30*C11,0) -> 0 | E11: 0 | F11: =B11-D11+E11 -> 0
A12: July | B12: 0 | C12: 0 | D12: =IF(C12>0,B12/30*C12,0) -> 0 | E12: 0 | F12: =B12-D12+E12 -> 0
A13: August | B13: 0 | C13: 0 | D13: =IF(C13>0,B13/30*C13,0) -> 0 | E13: 0 | F13: =B13-D13+E13 -> 0
A14: September | B14: 0 | C14: 0 | D14: =IF(C14>0,B14/30*C14,0) -> 0 | E14: 0 | F14: =B14-D14+E14 -> 0
A15: October | B15: 0 | C15: 0 | D15: =IF(C15>0,B15/30*C15,0) -> 0 | E15: 0 | F15: =B15-D15+E15 -> 0
A16: November | B16: 0 | C16: 0 | D16: =IF(C16>0,B16/30*C16,0) -> 0 | E16: 0 | F16: =B16-D16+E16 -> 0
A17: December | B17: 0 | C17: 0 | D17: =IF(C17>0,B17/30*C17,0) -> 0 | E17: 0 | F17: =B17-D17+E17 -> 0
A18: TOTAL | B18: =SUM(B6:B17) -> 0 | C18: =SUM(C6:C17) -> 0 | D18: =SUM(D6:D17) -> 0 | E18: =SUM(E6:E17) -> 0 | F18: =SUM(F6:F17) -> 0

Sheet Expenses
A1: SCHEDULE E EXPENSES
A3: Tax Year: | B3: =Dashboard!C6 -> 2025
A5: Line | B5: Category | C5: Jan | D5: Feb | E5: Mar | F5: Apr | G5: May | H5: Jun | I5: Jul | J5: Aug | K5: Sep | L5: Oct | M5: Nov | N5: Dec | O5: TOTAL
A6: 5 | B6: Advertising | C6: 0 | D6: 0 | E6: 0 | F6: 0 | G6: 0 | H6: 0 | I6: 0 | J6: 0 | K6: 0 | L6: 0 | M6: 0 | N6: 0 | O6: =SUM(C6:N6) -> 0
A7: 6 | B7: Auto & Travel | C7: 0 | D7: 0 | E7: 0 | F7: 0 | G7: 0 | H7: 0 | I7: 0 | J7: 0 | K7: 0 | L7: 0 | M7: 0 | N7: 0 | O7: =SUM(C7:N7) -> 0
A8: 7 | B8: Cleaning & Maintenance | C8: 0 | D8: 0 | E8: 0 | F8: 0 | G8: 0 | H8: 0 | I8: 0 | J8: 0 | K8: 0 | L8: 0 | M8: 0 | N8: 0 | O8: =SUM(C8:N8) -> 0
A9: 8 | B9: Commissions | C9: 0 | D9: 0 | E9: 0 | F9: 0 | G9: 0 | H9: 0 | I9: 0 | J9: 0 | K9: 0 | L9: 0 | M9: 0 | N9: 0 | O9: =SUM(C9:N9) -> 0
A10: 9 | B10: Insurance | C10: 0 | D10: 0 | E10: 0 | F10: 0 | G10: 0 | H10: 0 | I10: 0 | J10: 0 | K10: 0 | L10: 0 | M10: 0 | N10: 0 | O10: =SUM(C10:N10) -> 0
A11: 10 | B11: Legal & Professional | C11: 0 | D11: 0 | E11: 0 | F11: 0 | G11: 0 | H11: 0 | I11: 0 | J11: 0 | K11: 0 | L11: 0 | M11: 0 | N11: 0 | O11: =SUM(C11:N11) -> 0
A12: 11 | B12: Management Fees | C12: 0 | D12: 0 | E12: 0 | F12: 0 | G12: 0 | H12: 0 | I12: 0 | J12: 0 | K12: 0 | L12: 0 | M12: 0 | N12: 0 | O12: =SUM(C12:N12) -> 0
A13: 12 | B13: Mortgage Interest | C13: 0 | D13: 0 | E13: 0 | F13: 0 | G13: 0 | H13: 0 | I13: 0 | J13: 0 | K13: 0 | L13: 0 | M13: 0 | N13: 0 | O13: =SUM(C13:N13) -> 0
A14: 13 | B14: Other Interest | C14: 0 | D14: 0 | E14: 0 | F14: 0 | G14: 0 | H14: 0 | I14: 0 | J14: 0 | K14: 0 | L14: 0 | M14: 0 | N14: 0 | O14: =SUM(C14:N14) -> 0
A15: 14 | B15: Repairs | C15: 0 | D15: 0 | E15: 0 | F15: 0 | G15: 0 | H15: 0 | I15: 0 | J15: 0 | K15: 0 | L15: 0 | M15: 0 | N15: 0 | O15: =SUM(C15:N15) -> 0
A16: 15 | B16: Supplies | C16: 0 | D16: 0 | E16: 0 | F16: 0 | G16: 0 | H16: 0 | I16: 0 | J16: 0 | K16: 0 | L16: 0 | M16: 0 | N16: 0 | O16: =SUM(C16:N16) -> 0
A17: 16 | B17: Property Taxes | C17: 0 | D17: 0 | E17: 0 | F17: 0 | G17: 0 | H17: 0 | I17: 0 | J17: 0 | K17: 0 | L17: 0 | M17: 0 | N17: 0 | O17: =SUM(C17:N17) -> 0
... A20: 19 | B20: Other | C20: 0 | D20: 0 | E20: 0 | F20: 0 | G20: 0 | H20: 0 | I20: 0 | J20: 0 | K20: 0 | L20: 0 | M20: 0 | N20: 0 | O20: =SUM(C20:N20) -> 0
B21: TOTAL EXPENSES | C21: =SUM(C6:C20) -> 0 | D21: =SUM(D6:D20) -> 0 | E21: =SUM(E6:E20) -> 0 | F21: =SUM(F6:F20) -> 0 | G21: =SUM(G6:G20) -> 0 | H21: =SUM(H6:H20) -> 0 | I21: =SUM(I6:I20) -> 0 | J21: =SUM(J6:J20) -> 0 | ... O21: =SUM(O6:O20) -> 0

Sheet MAGI
A1: MAGI CALCULATOR
A3: Modified Adjusted Gross Income (MAGI) for ACA
A5: INCOME
A7: Gross Rental Income | C7: =Income!F18 -> 0
A9: Other Income (W-2, 1099, etc.) | C9: 0
A11: Total Expenses (Schedule E) | C11: =Expenses!O21 -> 0
A13: Net Rental Income | C13: =C7-C11 -> 0
A15: CALCULATED MAGI | C15: =C13+C9 -> 0
A17: TARGET COMPARISON
A19: Minimum for ACA (100% FPL) | C19: 15650
A20: Optimal Maximum (CSR 94%) | C20: 20121
A22: Distance from Minimum | C22: =C15-C19 -> -15650
A23: Headroom to Optimal Max | C23: =C20-C15 -> 20121
A25: QUALIFICATION STATUS
A27: Status: | C27: =IF(C15<15650,"COVERAGE GAP - Increase MAGI by "&TEXT(15650-C15,"$#,##0"),IF(C15<=20121,"OPTIMAL - Enrolled in CSR 94%",IF(C15<=23475,"OK - Still CSR 94%","WARNING - Above optimal range"))) -> COVERAGE GAP - Increase MAGI by $15,650
A29: Adjustment Needed: | C29: =IF(C15<15650,"REDUCE deductions by "&TEXT(15650-C15,"$#,##0"),IF(C15>20121,"INCREASE deductions by "&TEXT(C15-20121,"$#,##0"),"None - You are in the optimal range!")) -> REDUCE deductions by $15,650

Sheet Property
A1: PROPERTY INFORMATION
A3: Property Details (affects depreciation calculation)
A5: Address
A6: City | C6: Melbourne
A7: State | C7: FL
A8: ZIP
A9: Property Type | C9: Single Family
A10: Purchase Date
A11: Purchase Price | C11: 0
A12: Land Value (typically 20%) | C12: =IF(C11>0,C11*0.2,0) -> 0
A13: Building Value | C13: =IF(C11>0,C11-C12,0) -> 0
A14: Depreciation Years | C14: 27.5
A15: Annual Depreciation | C15: =IF(AND(C13>0,C14>0),C13/C14,0) -> 0
A17: Note: Enter Annual Depreciation in Expenses sheet, Line 18
A18: Note: Enter Annual Depreciation in Expenses sheet, Line 18

Sheet Recommendations
A1: TAX OPTIMIZATION RECOMMENDATIONS
A3: Current MAGI: | B3: =MAGI!C15 -> 0
A5: AUTOMATIC RECOMMENDATIONS
A7: If MAGI < $15,650: | B7: REDUCE DEDUCTIONS - You're in coverage gap!
B8: Defer repairs, don't prepay taxes
A9: If MAGI $15,650-$20,121: | B9: PERFECT - Maintain current expenses
B10: Enroll in FL Blue BlueOptions Silver PPO
A11: If MAGI $20,121-$23,475: | B11: STILL GOOD - Monitor closely
B12: You still qualify for CSR 94%
A13: If MAGI > $23,475: | B13: INCREASE DEDUCTIONS - Losing CSR benefits
B14: Prepay property taxes, accelerate repairs
A17: KEY DATES
A19: ACA Open Enrollment Ends: | B19: December 15, 2025
A20: Final Enrollment (Feb coverage): | B20: January 15, 2026
A21: Tax Filing Deadline: | B21: April 15, 2026
A24: RECOMMENDED PLAN
A26: Carrier: | B26: Florida Blue
A27: Plan: | B27: BlueOptions Silver PPO
A28: Network: | B28: Mayo Clinic Jacksonville ✓
A29: Estimated Premium: | B29: $0-50/month
A30: Deductible: | B30: $0
